viscore/__init__.py
viscore-0.0.1.dist-info/WHEEL
viscore-0.0.1.dist-info/METADATA
viscore-0.0.1.dist-info/RECORD
