Metadata-Version: 2.3
Name: viscore
Version: 0.0.1
Summary: Core library for Computer Vision research projects at the Mobile Perception Systems (MPS) lab at Eindhoven University of Technology (TU/e)
Requires-Python: >=3.13
